[
  {
    "id": 1,
    "name": "Plov (Osh)",
    "nameUz": "Osh",
    "description": "Traditional Uzbek rice dish with meat, carrots, and spices",
    "descriptionUz": "Go'sht, sabzi va ziravorlar bilan tayyorlangan an'anaviy o'zbek osh",
    "category": "Main Course",
    "price": 35000,
    "image": "/uzbek-plov-with-meat-and-carrots.jpg",
    "prepTime": "2 soat",
    "servings": 4,
    "rating": 4.9,
    "popular": true,
    "ingredients": ["Guruch", "Go'sht", "Sabzi", "Piyoz", "Zira", "Nok'at"]
  },
  {
    "id": 2,
    "name": "Lagman",
    "nameUz": "Lag'mon",
    "description": "Hand-pulled noodles with vegetables and meat in savory broth",
    "descriptionUz": "Sabzavotlar va go'sht bilan qo'l cho'zilgan noodles",
    "category": "Main Course",
    "price": 28000,
    "image": "/uzbek-lagman-noodles-with-vegetables.jpg",
    "prepTime": "1.5 soat",
    "servings": 2,
    "rating": 4.8,
    "popular": true,
    "ingredients": [
      "Lag'mon",
      "Go'sht",
      "Sabzavotlar",
      "Sarimsoq",
      "Ziravorlar"
    ]
  },
  {
    "id": 3,
    "name": "Manti",
    "nameUz": "Manti",
    "description": "Steamed dumplings filled with seasoned meat and onions",
    "descriptionUz": "Go'sht va piyoz bilan to'ldirilgan bug'da pishirilgan chuchvara",
    "category": "Main Course",
    "price": 25000,
    "image": "/uzbek-manti-steamed-dumplings.jpg",
    "prepTime": "1 soat",
    "servings": 3,
    "rating": 4.9,
    "popular": true,
    "ingredients": ["Xamir", "Qo'y go'shti", "Piyoz", "Ziravorlar"]
  },
  {
    "id": 4,
    "name": "Shashlik",
    "nameUz": "Shashlik",
    "description": "Grilled meat skewers marinated in spices",
    "descriptionUz": "Ziravorlarda marinadlangan va grilda pishirilgan kabob",
    "category": "Grill",
    "price": 30000,
    "image": "/uzbek-shashlik-grilled-meat-skewers.jpg",
    "prepTime": "45 daqiqa",
    "servings": 2,
    "rating": 4.8,
    "popular": true,
    "ingredients": ["Go'sht", "Piyoz", "Ziravorlar", "Sirka"]
  },
  {
    "id": 5,
    "name": "Samsa",
    "nameUz": "So'msa",
    "description": "Baked pastry filled with meat, onions, and spices",
    "descriptionUz": "Go'sht, piyoz va ziravorlar bilan to'ldirilgan pishirilgan xamir",
    "category": "Appetizer",
    "price": 8000,
    "image": "/uzbek-samsa-meat-pastry.jpg",
    "prepTime": "30 daqiqa",
    "servings": 1,
    "rating": 4.7,
    "popular": true,
    "ingredients": ["Xamir", "Go'sht", "Piyoz", "Zira"]
  },
  {
    "id": 6,
    "name": "Norin",
    "nameUz": "No'rin",
    "description": "Cold noodle dish with horse meat and vegetables",
    "descriptionUz": "Ot go'shti va sabzavotlar bilan sovuq noodles taomi",
    "category": "Main Course",
    "price": 32000,
    "image": "/uzbek-norin-cold-noodles.jpg",
    "prepTime": "2 soat",
    "servings": 3,
    "rating": 4.6,
    "popular": false,
    "ingredients": ["Xamir", "Ot go'shti", "Piyoz", "Ziravorlar"]
  },
  {
    "id": 7,
    "name": "Mastava",
    "nameUz": "Mastava",
    "description": "Rice soup with meat and vegetables",
    "descriptionUz": "Go'sht va sabzavotlar bilan guruch sho'rva",
    "category": "Soup",
    "price": 22000,
    "image": "/uzbek-mastava-rice-soup.jpg",
    "prepTime": "1 soat",
    "servings": 4,
    "rating": 4.7,
    "popular": false,
    "ingredients": ["Guruch", "Go'sht", "Sabzavotlar", "Ziravorlar"]
  },
  {
    "id": 8,
    "name": "Dimlama",
    "nameUz": "Dimlama",
    "description": "Slow-cooked stew with meat and vegetables",
    "descriptionUz": "Go'sht va sabzavotlar bilan sekin pishirilgan qovurma",
    "category": "Main Course",
    "price": 30000,
    "image": "/uzbek-dimlama-vegetable-stew.jpg",
    "prepTime": "2.5 soat",
    "servings": 4,
    "rating": 4.8,
    "popular": false,
    "ingredients": ["Go'sht", "Kartoshka", "Sabzi", "Pomidor", "Piyoz"]
  }
]
